onmqtt/__init__.py
onmqtt/onmqtt.py
onmqtt-0.5.dist-info/LICENSE.txt
onmqtt-0.5.dist-info/METADATA
onmqtt-0.5.dist-info/WHEEL
onmqtt-0.5.dist-info/top_level.txt
onmqtt-0.5.dist-info/RECORD
